{
  "hard": [
    {
      "title": "Flutter",
      "value": 95
    },
    {
      "title": "Java",
      "value": 85
    },
    {
      "title": "Go",
      "value": 80
    },
    {
      "title": "Swift",
      "value": 70
    },
    {
      "title": "Dart",
      "value": 95
    },
    {
      "title": "Kotlin",
      "value": 70
    },
    {
      "title": "SQL",
      "value": 80
    },
    {
      "title": "JavaScript",
      "value": 75
    },
    {
      "title": "HTML / CSS",
      "value": 90
    },
    {
      "title": "C",
      "value": 70
    }
  ],
  "soft": [
    {
      "title": "Management",
      "value": 85
    },
    {
      "title": "Leadership",
      "value": 90
    },
    {
      "title": "Architecture",
      "value": 90
    },
    {
      "title": "Version Control",
      "value": 95
    },
    {
      "title": "DevOps",
      "value": 80
    },
    {
      "title": "UI / UX",
      "value": 60
    },
    {
      "title": "Video Edition",
      "value": 60
    },
    {
      "title": "Image Edition",
      "value": 70
    }
  ]
}